odoo/addons/l10n_es_genci_sale/README.rst
odoo/addons/l10n_es_genci_sale/__init__.py
odoo/addons/l10n_es_genci_sale/__manifest__.py
odoo/addons/l10n_es_genci_sale/i18n/ca.po
odoo/addons/l10n_es_genci_sale/i18n/es.po
odoo/addons/l10n_es_genci_sale/models/__init__.py
odoo/addons/l10n_es_genci_sale/models/sale_order.py
odoo/addons/l10n_es_genci_sale/models/sale_order_line.py
odoo/addons/l10n_es_genci_sale/readme/CONTRIBUTORS.md
odoo/addons/l10n_es_genci_sale/readme/DESCRIPTION.md
odoo/addons/l10n_es_genci_sale/readme/INSTALL.md
odoo/addons/l10n_es_genci_sale/readme/ROADMAP.md
odoo/addons/l10n_es_genci_sale/readme/USAGE.md
odoo/addons/l10n_es_genci_sale/report/sale_report_template.xml
odoo/addons/l10n_es_genci_sale/static/description/icon.png
odoo/addons/l10n_es_genci_sale/static/description/index.html
odoo/addons/l10n_es_genci_sale/tests/__init__.py
odoo/addons/l10n_es_genci_sale/tests/test_l10n_es_genci_sale.py
odoo/addons/l10n_es_genci_sale/views/sale_order_views.xml
odoo_addon_l10n_es_genci_sale-16.0.1.0.0.1.dist-info/METADATA
odoo_addon_l10n_es_genci_sale-16.0.1.0.0.1.dist-info/WHEEL
odoo_addon_l10n_es_genci_sale-16.0.1.0.0.1.dist-info/top_level.txt
odoo_addon_l10n_es_genci_sale-16.0.1.0.0.1.dist-info/RECORD
