Metadata-Version: 2.1
Name: odoo-addon-l10n_es_genci_sale
Version: 16.0.1.0.0.1
Summary: Gestión tarifas GENCI - Ventas
Home-page: https://github.com/sygel-technology/sy-l10n-spain
Author: Sygel
License: AGPL-3
Classifier: Programming Language :: Python
Classifier: Framework :: Odoo
Classifier: Framework :: Odoo :: 16.0
Classifier: License :: OSI Approved :: GNU Affero General Public License v3
Requires-Python: >=3.10
Requires-Dist: odoo-addon-account-invoice-margin-sale<16.1dev,>=16.0dev
Requires-Dist: odoo-addon-l10n-es-genci-account<16.1dev,>=16.0dev
Requires-Dist: odoo<16.1dev,>=16.0a
